cpskin/__init__.py
cpskin/policy/__init__.py
cpskin/policy/config.py
cpskin/policy/configure.zcml
cpskin/policy/cropping.zcml
cpskin/policy/interfaces.py
cpskin/policy/overrides.zcml
cpskin/policy/profiles.zcml
cpskin/policy/setuphandlers.py
cpskin/policy/subscribers.py
cpskin/policy/testing.py
cpskin/policy/testing.zcml
cpskin/policy/upgrades.py
cpskin/policy/upgrades_data.py
cpskin/policy/browser/__init__.py
cpskin/policy/browser/configure.zcml
cpskin/policy/browser/migration.py
cpskin/policy/browser/pages.py
cpskin/policy/browser/rules.py
cpskin/policy/browser/templates/cookies.pt
cpskin/policy/profiles/default/browserlayer.xml
cpskin/policy/profiles/default/cpskin.policy-default.txt
cpskin/policy/profiles/default/cssregistry.xml
cpskin/policy/profiles/default/import_steps.xml
cpskin/policy/profiles/default/jsregistry.xml
cpskin/policy/profiles/default/metadata.xml
cpskin/policy/profiles/default/propertiestool.xml
cpskin/policy/profiles/default/registry.xml
cpskin/policy/profiles/default/theme.xml
cpskin/policy/profiles/default/types/Collection.xml
cpskin/policy/profiles/default/types/organization.xml
cpskin/policy/profiles/dx/metadata.xml
cpskin/policy/profiles/dx/types/Collection.xml
cpskin/policy/profiles/dx/types/Document.xml
cpskin/policy/profiles/dx/types/Event.xml
cpskin/policy/profiles/dx/types/Folder.xml
cpskin/policy/profiles/dx/types/News_Item.xml
cpskin/policy/profiles/testing/metadata.xml
cpskin/policy/profiles/uninstall/browserlayer.xml
cpskin/policy/profiles/uninstall/cpskin.policy-uninstall.txt
cpskin/policy/profiles/uninstall/import_steps.xml
cpskin/policy/profiles/uninstall/metadata.xml
cpskin/policy/profiles/uninstall/propertiestool.xml
cpskin/policy/profiles/uninstall/theme.xml
cpskin/policy/tests/__init__.py
cpskin/policy/tests/test_profiles.py
cpskin/policy/tests/test_robot.py
cpskin/policy/tests/robot/common.robot
cpskin/policy/tests/robot/navigation.robot
cpskin/policy/tests/robot/page.robot
cpskin.policy-4.3.58.dist-info/METADATA
cpskin.policy-4.3.58.dist-info/WHEEL
cpskin.policy-4.3.58.dist-info/top_level.txt
cpskin.policy-4.3.58.dist-info/RECORD
