Metadata-Version: 2.1
Name: cpskin.policy
Version: 4.3.58
Summary: Policy package for cpskin
Home-page: https://github.com/imio/cpskin.policy
Author: IMIO
Author-email: support@imio.be
License: gpl
Classifier: Environment :: Web Environment
Classifier: Programming Language :: Python
Classifier: Programming Language :: Python :: 2.7
Classifier: Framework :: Plone
Classifier: Framework :: Plone :: 4.2
Classifier: Framework :: Plone :: 4.3
Requires-Dist: setuptools
Requires-Dist: Plone
Requires-Dist: collective.contentrules.runscript
Requires-Dist: collective.geotransform
Requires-Dist: cpskin.agenda
Requires-Dist: cpskin.caching
Requires-Dist: cpskin.contenttypes
Requires-Dist: cpskin.core
Requires-Dist: cpskin.diazotheme.newDream
Requires-Dist: cpskin.menu
Requires-Dist: cpskin.minisite
Requires-Dist: cpskin.slider
Requires-Dist: cpskin.theme
Requires-Dist: cpskin.workflow
Requires-Dist: collective.directory
Requires-Dist: Products.PasswordStrength
Requires-Dist: collective.jekyll
Requires-Dist: Products.PloneFormGen
Requires-Dist: Products.PloneGazette
Requires-Dist: Solgema.fullcalendar
Requires-Dist: collective.atomrss
Requires-Dist: collective.monitor
Requires-Dist: collective.cookiecuttr
Requires-Dist: plone.app.imagecropping
Requires-Dist: imio.migrator
Requires-Dist: collective.excelexport
Requires-Dist: collective.autoscaling
Requires-Dist: collective.preventactions
Requires-Dist: collective.recaptcha
Requires-Dist: collective.sendinblue
Requires-Dist: collective.limitfilesizepanel
Requires-Dist: plone.restapi
Requires-Dist: collective.behavior.targetblank
Requires-Dist: collective.autopublishing
Requires-Dist: collective.folderishtypes
Requires-Dist: pas.plugins.imio
Requires-Dist: collective.captchacontactinfo
Requires-Dist: imio.prometheus
Requires-Dist: collective.anysurfer
Provides-Extra: test
Requires-Dist: plone.app.robotframework ; extra == 'test'
Requires-Dist: cpskin.demo ; extra == 'test'
Requires-Dist: plone.app.multilingual ; extra == 'test'
Requires-Dist: Products.contentmigration ; extra == 'test'
